MANIFEST.in
README.txt
setup.cfg
setup.py
wwp/__init__.py
wwp.shopfronts.egg-info/PKG-INFO
wwp.shopfronts.egg-info/SOURCES.txt
wwp.shopfronts.egg-info/dependency_links.txt
wwp.shopfronts.egg-info/entry_points.txt
wwp.shopfronts.egg-info/namespace_packages.txt
wwp.shopfronts.egg-info/not-zip-safe
wwp.shopfronts.egg-info/paster_plugins.txt
wwp.shopfronts.egg-info/requires.txt
wwp.shopfronts.egg-info/top_level.txt
wwp/shopfronts/README.txt
wwp/shopfronts/__init__.py
wwp/shopfronts/config.py
wwp/shopfronts/configure.zcml
wwp/shopfronts/browser/__init__.py
wwp/shopfronts/browser/configure.zcml
wwp/shopfronts/browser/shop_frontview.pt
wwp/shopfronts/browser/shop_frontview.py
wwp/shopfronts/browser/street_viewview.pt
wwp/shopfronts/browser/street_viewview.py
wwp/shopfronts/browser/images/def_logo.png
wwp/shopfronts/browser/images/def_shop.jpg
wwp/shopfronts/browser/images/def_street.jpg
wwp/shopfronts/content/__init__.py
wwp/shopfronts/content/configure.zcml
wwp/shopfronts/content/shop_front.py
wwp/shopfronts/content/street_view.py
wwp/shopfronts/interfaces/__init__.py
wwp/shopfronts/interfaces/shop_front.py
wwp/shopfronts/interfaces/street_view.py
wwp/shopfronts/portlets/__init__.py
wwp/shopfronts/portlets/configure.zcml
wwp/shopfronts/profiles/default/factorytool.xml
wwp/shopfronts/profiles/default/metadata.xml
wwp/shopfronts/profiles/default/portlets.xml
wwp/shopfronts/profiles/default/rolemap.xml
wwp/shopfronts/profiles/default/types.xml
wwp/shopfronts/profiles/default/types/shop_front.xml
wwp/shopfronts/profiles/default/types/street_view.xml
wwp/shopfronts/tests/__init__.py
wwp/shopfronts/tests/base.py
wwp/shopfronts/tests/test_doctest.py