Metadata-Version: 1.0
Name: wwp.shopfronts
Version: 0.6dev
Summary: Display online shopfronts
Home-page: http://svn.plone.org/svn/plone/plone.example
Author: Peter Dyson
Author-email: pjdyson@gmail.com
License: GPL
Keywords: wwp plone zope shop shopfront store shopfronts
Platform: UNKNOWN
Classifier: Framework :: Plone
Classifier: Intended Audience :: Developers
Classifier: Topic :: Software Development :: Libraries :: Python Modules
Classifier: License :: OSI Approved :: GNU General Public License (GPL)
